./.dockerignore
./.gitignore
./.python-version
./Dockerfile
./PKG-INFO
./api.py
./cleanup.py
./config.py
./config.yaml
./database.py
./docker-compose.yml
./main.py
./monitor.py
./pyproject.toml
./pytest.ini
./test-integrated-deployment.sh
./uv.lock
./frontend/.env.development
./frontend/.gitignore
./frontend/index.html
./frontend/dist/index.html
./frontend/dist/assets/index-CvLCQukK.css
./frontend/dist/assets/index-DN3C8_Oh.js
ace_network_monitor-0.3.2.dist-info/METADATA
ace_network_monitor-0.3.2.dist-info/WHEEL
ace_network_monitor-0.3.2.dist-info/entry_points.txt
ace_network_monitor-0.3.2.dist-info/RECORD
