Metadata-Version: 2.4
Name: ace-network-monitor
Version: 0.3.2
Summary: Network connectivity monitoring tool with ping statistics, outage tracking, FastAPI backend and Vue.js dashboard
Project-URL: Homepage, https://github.com/ACE-IoT-Solutions/ace-network-monitor
Project-URL: Repository, https://github.com/ACE-IoT-Solutions/ace-network-monitor
Project-URL: Documentation, https://github.com/ACE-IoT-Solutions/ace-network-monitor#readme
Project-URL: Issues, https://github.com/ACE-IoT-Solutions/ace-network-monitor/issues
Author-email: ACE IoT Solutions <info@aceiotsolutions.com>
License: MIT
Keywords: dashboard,fastapi,latency,monitoring,networking,ping,vue
Classifier: Development Status :: 4 - Beta
Classifier: Intended Audience :: Developers
Classifier: Intended Audience :: System Administrators
Classifier: License :: OSI Approved :: MIT License
Classifier: Programming Language :: Python :: 3
Classifier: Programming Language :: Python :: 3.9
Classifier: Programming Language :: Python :: 3.10
Classifier: Programming Language :: Python :: 3.11
Classifier: Programming Language :: Python :: 3.12
Classifier: Topic :: System :: Monitoring
Classifier: Topic :: System :: Networking :: Monitoring
Requires-Python: >=3.9
Requires-Dist: click>=8.0.0
Requires-Dist: fastapi>=0.104.0
Requires-Dist: pydantic>=2.0.0
Requires-Dist: pyyaml>=6.0
Requires-Dist: schedule>=1.1.0
Requires-Dist: uvicorn[standard]>=0.24.0
